ament_cmake_ros_core/_dummy.cpython-310-x86_64-linux-gnu.so
ros_ament_cmake_ros_core-0.14.5.data/data/share/ament_cmake_ros_core/local_setup.bash
ros_ament_cmake_ros_core-0.14.5.data/data/share/ament_cmake_ros_core/local_setup.dsv
ros_ament_cmake_ros_core-0.14.5.data/data/share/ament_cmake_ros_core/local_setup.sh
ros_ament_cmake_ros_core-0.14.5.data/data/share/ament_cmake_ros_core/local_setup.zsh
ros_ament_cmake_ros_core-0.14.5.data/data/share/ament_cmake_ros_core/package.dsv
ros_ament_cmake_ros_core-0.14.5.data/data/share/ament_cmake_ros_core/package.xml
ros_ament_cmake_ros_core-0.14.5.data/data/share/ament_cmake_ros_core/cmake/ament_cmake_export_dependencies-extras.cmake
ros_ament_cmake_ros_core-0.14.5.data/data/share/ament_cmake_ros_core/cmake/ament_cmake_ros_core-extras.cmake
ros_ament_cmake_ros_core-0.14.5.data/data/share/ament_cmake_ros_core/cmake/ament_cmake_ros_coreConfig-version.cmake
ros_ament_cmake_ros_core-0.14.5.data/data/share/ament_cmake_ros_core/cmake/ament_cmake_ros_coreConfig.cmake
ros_ament_cmake_ros_core-0.14.5.data/data/share/ament_cmake_ros_core/cmake/build_shared_libs.cmake
ros_ament_cmake_ros_core-0.14.5.data/data/share/ament_cmake_ros_core/environment/ament_prefix_path.dsv
ros_ament_cmake_ros_core-0.14.5.data/data/share/ament_cmake_ros_core/environment/ament_prefix_path.sh
ros_ament_cmake_ros_core-0.14.5.data/data/share/ament_cmake_ros_core/environment/path.dsv
ros_ament_cmake_ros_core-0.14.5.data/data/share/ament_cmake_ros_core/environment/path.sh
ros_ament_cmake_ros_core-0.14.5.data/data/share/ament_index/resource_index/package_run_dependencies/ament_cmake_ros_core
ros_ament_cmake_ros_core-0.14.5.data/data/share/ament_index/resource_index/packages/ament_cmake_ros_core
ros_ament_cmake_ros_core-0.14.5.data/data/share/ament_index/resource_index/parent_prefix_path/ament_cmake_ros_core
ros_ament_cmake_ros_core-0.14.5.dist-info/METADATA
ros_ament_cmake_ros_core-0.14.5.dist-info/WHEEL
ros_ament_cmake_ros_core-0.14.5.dist-info/top_level.txt
ros_ament_cmake_ros_core-0.14.5.dist-info/RECORD
