Metadata-Version: 2.4
Name: ros-ament-cmake-ros-core
Version: 0.14.5
Summary: Wheel for the ament_cmake_ros_core (ros-ament-cmake-ros-core) ROS 2 package.
Dynamic: description
Dynamic: description-content-type
Dynamic: summary
